pylogu/__init__.py
pylogu/client.py
pylogu/http.py
pylogu/setup.py
pylogu/core/__init__.py
pylogu/core/config.py
pylogu-0.2.4.dist-info/METADATA
pylogu-0.2.4.dist-info/WHEEL
pylogu-0.2.4.dist-info/top_level.txt
pylogu-0.2.4.dist-info/RECORD
